{
    "大觀二#1": {
        "energy_storage_sum": 1769.6,
        "energy_storage_count": 12,
        "energy_storage_load_sum": 0,
        "energy_storage_load_count": 0
    },
    "明潭#2": {
        "energy_storage_sum": 1827,
        "energy_storage_count": 12,
        "energy_storage_load_sum": 0,
        "energy_storage_load_count": 0
    },
    "電池(註16)": {
        "energy_storage_sum": 94.8,
        "energy_storage_count": 2,
        "energy_storage_load_sum": 0,
        "energy_storage_load_count": 0
    }
}