{
    "明潭#2": {
        "energy_storage_sum": 346.4,
        "energy_storage_count": 2,
        "energy_storage_load_sum": 0,
        "energy_storage_load_count": 0
    },
    "明潭#3": {
        "energy_storage_sum": 176.3,
        "energy_storage_count": 1,
        "energy_storage_load_sum": 0,
        "energy_storage_load_count": 0
    },
    "電池(註16)": {
        "energy_storage_sum": 44,
        "energy_storage_count": 3,
        "energy_storage_load_sum": 297.9,
        "energy_storage_load_count": 9
    },
    "大觀二#2": {
        "energy_storage_sum": 0,
        "energy_storage_count": 0,
        "energy_storage_load_sum": 2509.7,
        "energy_storage_load_count": 11
    },
    "明潭#4": {
        "energy_storage_sum": 0,
        "energy_storage_count": 0,
        "energy_storage_load_sum": 1318.8,
        "energy_storage_load_count": 5
    },
    "大觀二#1": {
        "energy_storage_sum": 0,
        "energy_storage_count": 0,
        "energy_storage_load_sum": 954.2,
        "energy_storage_load_count": 4
    }
}