[
    {
        "time": "133000",
        "generators": [
            "核二Gas1"
        ],
        "count": 1
    },
    {
        "time": "134000",
        "generators": [
            "核二Gas1"
        ],
        "count": 1
    },
    {
        "time": "152000",
        "generators": [
            "核二Gas2"
        ],
        "count": 1
    },
    {
        "time": "153000",
        "generators": [
            "核二Gas2"
        ],
        "count": 1
    },
    {
        "time": "154000",
        "generators": [
            "核二Gas2"
        ],
        "count": 1
    }
]