{
    "大觀二#1": {
        "energy_storage_sum": 7876.4,
        "energy_storage_count": 53,
        "energy_storage_load_sum": 0,
        "energy_storage_load_count": 0
    },
    "大觀二#2": {
        "energy_storage_sum": 1028,
        "energy_storage_count": 7,
        "energy_storage_load_sum": 0,
        "energy_storage_load_count": 0
    },
    "明潭#2": {
        "energy_storage_sum": 3529,
        "energy_storage_count": 24,
        "energy_storage_load_sum": 0,
        "energy_storage_load_count": 0
    },
    "明潭#3": {
        "energy_storage_sum": 6184.8,
        "energy_storage_count": 35,
        "energy_storage_load_sum": 0,
        "energy_storage_load_count": 0
    },
    "明潭#4": {
        "energy_storage_sum": 9778,
        "energy_storage_count": 65,
        "energy_storage_load_sum": 0,
        "energy_storage_load_count": 0
    },
    "電池(註16)": {
        "energy_storage_sum": 10178,
        "energy_storage_count": 50,
        "energy_storage_load_sum": 0,
        "energy_storage_load_count": 0
    },
    "大觀二#4": {
        "energy_storage_sum": 7896.2,
        "energy_storage_count": 52,
        "energy_storage_load_sum": 0,
        "energy_storage_load_count": 0
    },
    "明潭#1": {
        "energy_storage_sum": 8357.5,
        "energy_storage_count": 47,
        "energy_storage_load_sum": 0,
        "energy_storage_load_count": 0
    },
    "大觀二#3": {
        "energy_storage_sum": 1537.3,
        "energy_storage_count": 10,
        "energy_storage_load_sum": 0,
        "energy_storage_load_count": 0
    },
    "明潭#6": {
        "energy_storage_sum": 602.5,
        "energy_storage_count": 4,
        "energy_storage_load_sum": 0,
        "energy_storage_load_count": 0
    }
}