{
    "明潭#1": {
        "energy_storage_sum": 348.5,
        "energy_storage_count": 2,
        "energy_storage_load_sum": 1063.8,
        "energy_storage_load_count": 4
    },
    "明潭#4": {
        "energy_storage_sum": 580.9,
        "energy_storage_count": 4,
        "energy_storage_load_sum": 1313.7,
        "energy_storage_load_count": 5
    },
    "電池(註16)": {
        "energy_storage_sum": 74.5,
        "energy_storage_count": 3,
        "energy_storage_load_sum": 188.3,
        "energy_storage_load_count": 9
    },
    "大觀二#2": {
        "energy_storage_sum": 0,
        "energy_storage_count": 0,
        "energy_storage_load_sum": 2212.2,
        "energy_storage_load_count": 9
    },
    "明潭#2": {
        "energy_storage_sum": 0,
        "energy_storage_count": 0,
        "energy_storage_load_sum": 1845.2,
        "energy_storage_load_count": 7
    },
    "大觀二#3": {
        "energy_storage_sum": 0,
        "energy_storage_count": 0,
        "energy_storage_load_sum": 241.9,
        "energy_storage_load_count": 1
    }
}