{
    "明潭#3": {
        "energy_storage_sum": 5845.3,
        "energy_storage_count": 32,
        "energy_storage_load_sum": 0,
        "energy_storage_load_count": 0
    },
    "明潭#4": {
        "energy_storage_sum": 5833,
        "energy_storage_count": 33,
        "energy_storage_load_sum": 0,
        "energy_storage_load_count": 0
    },
    "電池(註16)": {
        "energy_storage_sum": 8804.8,
        "energy_storage_count": 41,
        "energy_storage_load_sum": 0,
        "energy_storage_load_count": 0
    },
    "大觀二#1": {
        "energy_storage_sum": 5609.9,
        "energy_storage_count": 33,
        "energy_storage_load_sum": 0,
        "energy_storage_load_count": 0
    },
    "大觀二#2": {
        "energy_storage_sum": 3025.1,
        "energy_storage_count": 16,
        "energy_storage_load_sum": 0,
        "energy_storage_load_count": 0
    },
    "明潭#5": {
        "energy_storage_sum": 2775,
        "energy_storage_count": 15,
        "energy_storage_load_sum": 0,
        "energy_storage_load_count": 0
    },
    "大觀二#4": {
        "energy_storage_sum": 3379.6,
        "energy_storage_count": 19,
        "energy_storage_load_sum": 0,
        "energy_storage_load_count": 0
    },
    "明潭#6": {
        "energy_storage_sum": 4017.9,
        "energy_storage_count": 21,
        "energy_storage_load_sum": 0,
        "energy_storage_load_count": 0
    },
    "大觀二#3": {
        "energy_storage_sum": 1107.3,
        "energy_storage_count": 6,
        "energy_storage_load_sum": 0,
        "energy_storage_load_count": 0
    }
}