{
    "明潭#2": {
        "energy_storage_sum": 618.2,
        "energy_storage_count": 5,
        "energy_storage_load_sum": 14004.9,
        "energy_storage_load_count": 54
    },
    "明潭#4": {
        "energy_storage_sum": 4951.7,
        "energy_storage_count": 33,
        "energy_storage_load_sum": 6837.3,
        "energy_storage_load_count": 26
    },
    "電池(註16)": {
        "energy_storage_sum": 3051.4,
        "energy_storage_count": 35,
        "energy_storage_load_sum": 10490.2,
        "energy_storage_load_count": 66
    },
    "大觀二#3": {
        "energy_storage_sum": 1500.2,
        "energy_storage_count": 10,
        "energy_storage_load_sum": 12567.5,
        "energy_storage_load_count": 54
    },
    "大觀二#2": {
        "energy_storage_sum": 1632.6,
        "energy_storage_count": 11,
        "energy_storage_load_sum": 8603.7,
        "energy_storage_load_count": 36
    },
    "明潭#3": {
        "energy_storage_sum": 0,
        "energy_storage_count": 0,
        "energy_storage_load_sum": 12687.6,
        "energy_storage_load_count": 50
    },
    "大觀二#4": {
        "energy_storage_sum": 3853.7,
        "energy_storage_count": 26,
        "energy_storage_load_sum": 0,
        "energy_storage_load_count": 0
    },
    "明潭#6": {
        "energy_storage_sum": 581.8,
        "energy_storage_count": 4,
        "energy_storage_load_sum": 1830.1,
        "energy_storage_load_count": 7
    },
    "明潭#1": {
        "energy_storage_sum": 0,
        "energy_storage_count": 0,
        "energy_storage_load_sum": 1792.4,
        "energy_storage_load_count": 7
    },
    "大觀二#1": {
        "energy_storage_sum": 2263.1,
        "energy_storage_count": 15,
        "energy_storage_load_sum": 0,
        "energy_storage_load_count": 0
    }
}