{
    "電池(註16)": {
        "energy_storage_sum": 39.3,
        "energy_storage_count": 3,
        "energy_storage_load_sum": 338.1,
        "energy_storage_load_count": 8
    },
    "大觀二#2": {
        "energy_storage_sum": 0,
        "energy_storage_count": 0,
        "energy_storage_load_sum": 2728,
        "energy_storage_load_count": 11
    },
    "明潭#3": {
        "energy_storage_sum": 0,
        "energy_storage_count": 0,
        "energy_storage_load_sum": 2881.8,
        "energy_storage_load_count": 11
    },
    "明潭#2": {
        "energy_storage_sum": 0,
        "energy_storage_count": 0,
        "energy_storage_load_sum": 1060.5,
        "energy_storage_load_count": 4
    }
}