{
    "timestamp": "2025-09-22 10:50",
    "active_emergency_generators": [
        {
            "name": "興達#3(註12)",
            "pattern": "興達#3",
            "output": "227.3",
            "percentage": "41.327%",
            "status": "",
            "timestamp": "2025-09-22 10:50"
        },
        {
            "name": "興達#4(註12)",
            "pattern": "興達#4",
            "output": "380.0",
            "percentage": "69.091%",
            "status": "",
            "timestamp": "2025-09-22 10:50"
        }
    ],
    "total_count": 2,
    "created_at": "2025-09-22 11:02:04"
}