{
    "大觀二#2": {
        "energy_storage_sum": 0,
        "energy_storage_count": 0,
        "energy_storage_load_sum": 11736.2,
        "energy_storage_load_count": 49
    },
    "大觀二#3": {
        "energy_storage_sum": 0,
        "energy_storage_count": 0,
        "energy_storage_load_sum": 11958.4,
        "energy_storage_load_count": 50
    },
    "明潭#3": {
        "energy_storage_sum": 886.3,
        "energy_storage_count": 5,
        "energy_storage_load_sum": 12266.9,
        "energy_storage_load_count": 48
    },
    "明潭#4": {
        "energy_storage_sum": 0,
        "energy_storage_count": 0,
        "energy_storage_load_sum": 13731,
        "energy_storage_load_count": 53
    },
    "電池(註16)": {
        "energy_storage_sum": 344.5,
        "energy_storage_count": 10,
        "energy_storage_load_sum": 12621.8,
        "energy_storage_load_count": 63
    },
    "明潭#5": {
        "energy_storage_sum": 0,
        "energy_storage_count": 0,
        "energy_storage_load_sum": 11278.2,
        "energy_storage_load_count": 43
    },
    "明潭#2": {
        "energy_storage_sum": 2801.9,
        "energy_storage_count": 19,
        "energy_storage_load_sum": 10147,
        "energy_storage_load_count": 39
    },
    "大觀二#4": {
        "energy_storage_sum": 1774.9,
        "energy_storage_count": 12,
        "energy_storage_load_sum": 4646.1,
        "energy_storage_load_count": 20
    }
}